EcosDataReader/__init__.py
EcosDataReader/fetcher.py
EcosDataReader/reader.py
EcosDataReader/data_reader/__init__.py
EcosDataReader/data_reader/_data_reader.py
EcosDataReader/data_reader/bank.py
EcosDataReader/data_reader/economic_index.py
EcosDataReader/data_reader/foreign_currency.py
EcosDataReader/data_reader/global_index.py
EcosDataReader/data_reader/interest.py
EcosDataReader/data_reader/market.py
EcosDataReader/data_reader/monetary.py
EcosDataReader/data_reader/payment.py
EcosDataReader/data_reader/price_index.py
EcosDataReader/data_reader/trade.py
EcosDataReader-1.0.0.dist-info/METADATA
EcosDataReader-1.0.0.dist-info/WHEEL
EcosDataReader-1.0.0.dist-info/top_level.txt
EcosDataReader-1.0.0.dist-info/RECORD
